[
  {
    "arguments": [
      "/usr/bin/clang",
      "-c",
      "-I/usr/include/python3.12",
      "-I/usr/include/python3.12",
      "-fno-strict-overflow",
      "-Wsign-compare",
      "-DNDEBUG",
      "-g",
      "-O2",
      "-Wall",
      "-Wall",
      "-Wextra",
      "-Wswitch",
      "-Wswitch-enum",
      "-o",
      "py",
      "test.c"
    ],
    "directory": "/mnt/coding/qgum",
    "file": "/mnt/coding/qgum/test.c",
    "output": "/mnt/coding/qgum/py"
  },
  {
    "arguments": [
      "/usr/lib/llvm-18/bin/clang",
      "-cc1",
      "-triple",
      "x86_64-pc-linux-gnu",
      "-emit-obj",
      "-dumpdir",
      "py-",
      "-disable-free",
      "-clear-ast-before-backend",
      "-disable-llvm-verifier",
      "-discard-value-names",
      "-main-file-name",
      "-mrelocation-model",
      "pic",
      "-pic-level",
      "2",
      "-pic-is-pie",
      "-mframe-pointer=none",
      "-fmath-errno",
      "-ffp-contract=on",
      "-fno-rounding-math",
      "-mconstructor-aliases",
      "-funwind-tables=2",
      "-target-cpu",
      "x86-64",
      "-tune-cpu",
      "generic",
      "-debug-info-kind=constructor",
      "-dwarf-version=5",
      "-debugger-tuning=gdb",
      "-fdebug-compilation-dir=/mnt/coding/qgum",
      "-fcoverage-compilation-dir=/mnt/coding/qgum",
      "-resource-dir",
      "/usr/lib/llvm-18/lib/clang/18",
      "-I",
      "/usr/include/python3.12",
      "-I",
      "/usr/include/python3.12",
      "-D",
      "NDEBUG",
      "-internal-isystem",
      "/usr/lib/llvm-18/lib/clang/18/include",
      "-internal-isystem",
      "/usr/local/include",
      "-internal-isystem",
      "/usr/bin/../lib/gcc/x86_64-linux-gnu/14/../../../../x86_64-linux-gnu/include",
      "-internal-externc-isystem",
      "/usr/include/x86_64-linux-gnu",
      "-internal-externc-isystem",
      "/include",
      "-internal-externc-isystem",
      "/usr/include",
      "-O2",
      "-Wsign-compare",
      "-Wall",
      "-Wall",
      "-Wextra",
      "-Wswitch",
      "-Wswitch-enum",
      "-ferror-limit",
      "19",
      "-fwrapv",
      "-fgnuc-version=4.2.1",
      "-fskip-odr-check-in-gmf",
      "-fcolor-diagnostics",
      "-vectorize-loops",
      "-vectorize-slp",
      "-faddrsig",
      "-D__GCC_HAVE_DWARF2_CFI_ASM=1",
      "-x",
      "c",
      "-o",
      "/tmp/test-162c9e.o",
      "test.c"
    ],
    "directory": "/mnt/coding/qgum",
    "file": "/mnt/coding/qgum/test.c",
    "output": "/tmp/test-162c9e.o"
  },
  {
    "arguments": [
      "/usr/bin/clang",
      "-c",
      "-Ideps/mlib",
      "-Ideps/clog",
      "-Wall",
      "-Wextra",
      "-Wswitch",
      "-Wswitch-enum",
      "-fsanitize=address,undefined",
      "-o",
      "parser",
      "parser.c"
    ],
    "directory": "/mnt/coding/qgum",
    "file": "/mnt/coding/qgum/parser.c",
    "output": "/mnt/coding/qgum/parser"
  },
  {
    "arguments": [
      "/usr/lib/llvm-18/bin/clang",
      "-cc1",
      "-triple",
      "x86_64-pc-linux-gnu",
      "-emit-obj",
      "-mrelax-all",
      "-dumpdir",
      "parser-",
      "-disable-free",
      "-clear-ast-before-backend",
      "-disable-llvm-verifier",
      "-discard-value-names",
      "-main-file-name",
      "-mrelocation-model",
      "pic",
      "-pic-level",
      "2",
      "-pic-is-pie",
      "-mframe-pointer=all",
      "-fmath-errno",
      "-ffp-contract=on",
      "-fno-rounding-math",
      "-mconstructor-aliases",
      "-funwind-tables=2",
      "-target-cpu",
      "x86-64",
      "-tune-cpu",
      "generic",
      "-debugger-tuning=gdb",
      "-fdebug-compilation-dir=/mnt/coding/qgum",
      "-fcoverage-compilation-dir=/mnt/coding/qgum",
      "-resource-dir",
      "/usr/lib/llvm-18/lib/clang/18",
      "-I",
      "deps/mlib",
      "-I",
      "deps/clog",
      "-internal-isystem",
      "/usr/lib/llvm-18/lib/clang/18/include",
      "-internal-isystem",
      "/usr/local/include",
      "-internal-isystem",
      "/usr/bin/../lib/gcc/x86_64-linux-gnu/14/../../../../x86_64-linux-gnu/include",
      "-internal-externc-isystem",
      "/usr/include/x86_64-linux-gnu",
      "-internal-externc-isystem",
      "/include",
      "-internal-externc-isystem",
      "/usr/include",
      "-Wall",
      "-Wextra",
      "-Wswitch",
      "-Wswitch-enum",
      "-ferror-limit",
      "19",
      "-fsanitize=address,alignment,array-bounds,bool,builtin,enum,float-cast-overflow,function,integer-divide-by-zero,nonnull-attribute,null,pointer-overflow,return,returns-nonnull-attribute,shift-base,shift-exponent,signed-integer-overflow,unreachable,vla-bound,vptr",
      "-fsanitize-recover=alignment,array-bounds,bool,builtin,enum,float-cast-overflow,function,integer-divide-by-zero,nonnull-attribute,null,pointer-overflow,returns-nonnull-attribute,shift-base,shift-exponent,signed-integer-overflow,vla-bound,vptr",
      "-fsanitize-system-ignorelist=/usr/lib/llvm-18/lib/clang/18/share/asan_ignorelist.txt",
      "-fno-sanitize-memory-param-retval",
      "-fsanitize-address-use-after-scope",
      "-fsanitize-address-globals-dead-stripping",
      "-fno-assume-sane-operator-new",
      "-fgnuc-version=4.2.1",
      "-fskip-odr-check-in-gmf",
      "-fcolor-diagnostics",
      "-faddrsig",
      "-D__GCC_HAVE_DWARF2_CFI_ASM=1",
      "-x",
      "c",
      "-o",
      "/tmp/parser-e8e86f.o",
      "parser.c"
    ],
    "directory": "/mnt/coding/qgum",
    "file": "/mnt/coding/qgum/parser.c",
    "output": "/tmp/parser-e8e86f.o"
  }
]
